{
    "consumes": [
        "application/json"
    ],
    "produces": [
        "application/json"
    ],
    "schemes": [
        "https"
    ],
    "swagger": "2.0",
    "info": {
        "description": "Create, modify, delete and retrieve research notes.",
        "title": "Research Note",
        "version": "1.0.0",
        "x-aladdin-api-id": "agraph.investment_research.content.research_note.ResearchNoteAPI",
        "x-aladdin-api-stability": "alpha",
        "x-aladdin-spec-id": "agraph.investment_research.content.research_note.v1.ResearchNoteAPI"
    },
    "basePath": "/api/investment-research/content/research-note/v1/",
    "paths": {
        "/researchNotes": {
            "post": {
                "description": "Creates a research note",
                "summary": "Creates a research note",
                "operationId": "ResearchNoteAPI_CreateResearchNote",
                "parameters": [
                    {
                        "type": "string",
                        "format": "UUID",
                        "description": "A unique identifier for this request.",
                        "name": "VND.com.blackrock.Request-ID",
                        "in": "header",
                        "required": true
                    },
                    {
                        "type": "string",
                        "format": "date-time",
                        "description": "Timestamp assigned to this request at origin, in \"HTTP-date\" format as defined by RFC 7231.",
                        "name": "VND.com.blackrock.Origin-Timestamp",
                        "in": "header",
                        "required": true
                    },
                    {
                        "description": "research to create.",
                        "name": "body",
                        "in": "body",
                        "required": true,
                        "schema": {
                            "$ref": "#/definitions/v1ResearchNote"
                        }
                    }
                ],
                "responses": {
                    "200": {
                        "description": "A successful response.",
                        "schema": {
                            "$ref": "#/definitions/v1ResearchNote"
                        }
                    },
                    "400": {
                        "description": "Aladdin® will not process the request due to an apparent client error.",
                        "schema": {
                            "description": "Defines an error that occurred.",
                            "type": "object",
                            "required": [
                                "code",
                                "message"
                            ],
                            "properties": {
                                "code": {
                                    "description": "A short mnemonic reference code for the error.",
                                    "type": "string",
                                    "maxLength": 40
                                },
                                "message": {
                                    "description": "A human readable description of the error.",
                                    "type": "string"
                                }
                            }
                        },
                        "headers": {
                            "VND.com.blackrock.Request-ID": {
                                "type": "string",
                                "format": "UUID",
                                "description": "The unique identifier assigned by the client to the request that originated this response."
                            },
                            "VND.com.blackrock.Response-ID": {
                                "type": "string",
                                "format": "UUID",
                                "description": "A Unique Identifier for this response."
                            },
                            "VND.com.blackrock.Response-Timestamp": {
                                "type": "string",
                                "format": "date-time",
                                "description": "Timestamp assigned to this response, in \"HTTP-date\" format as defined by RFC 7231."
                            }
                        }
                    },
                    "401": {
                        "description": "Aladdin® will not process the request as the necessary credentials were not provided or were invalid.",
                        "schema": {
                            "description": "Defines an error that occurred.",
                            "type": "object",
                            "required": [
                                "code",
                                "message"
                            ],
                            "properties": {
                                "code": {
                                    "description": "A short mnemonic reference code for the error.",
                                    "type": "string",
                                    "maxLength": 40
                                },
                                "message": {
                                    "description": "A human readable description of the error.",
                                    "type": "string"
                                }
                            }
                        },
                        "headers": {
                            "VND.com.blackrock.Request-ID": {
                                "type": "string",
                                "format": "UUID",
                                "description": "The unique identifier assigned by the client to the request that originated this response."
                            },
                            "VND.com.blackrock.Response-ID": {
                                "type": "string",
                                "format": "UUID",
                                "description": "A Unique Identifier for this response."
                            },
                            "VND.com.blackrock.Response-Timestamp": {
                                "type": "string",
                                "format": "date-time",
                                "description": "Timestamp assigned to this response, in \"HTTP-date\" format as defined by RFC 7231."
                            }
                        }
                    },
                    "403": {
                        "description": "Aladdin® understood the request but is refusing to authorize it.",
                        "schema": {
                            "description": "Defines an error that occurred.",
                            "type": "object",
                            "required": [
                                "code",
                                "message"
                            ],
                            "properties": {
                                "code": {
                                    "description": "A short mnemonic reference code for the error.",
                                    "type": "string",
                                    "maxLength": 40
                                },
                                "message": {
                                    "description": "A human readable description of the error.",
                                    "type": "string"
                                }
                            }
                        },
                        "headers": {
                            "VND.com.blackrock.Request-ID": {
                                "type": "string",
                                "format": "UUID",
                                "description": "The unique identifier assigned by the client to the request that originated this response."
                            },
                            "VND.com.blackrock.Response-ID": {
                                "type": "string",
                                "format": "UUID",
                                "description": "A Unique Identifier for this response."
                            },
                            "VND.com.blackrock.Response-Timestamp": {
                                "type": "string",
                                "format": "date-time",
                                "description": "Timestamp assigned to this response, in \"HTTP-date\" format as defined by RFC 7231."
                            }
                        }
                    },
                    "404": {
                        "description": "Aladdin® did not find the resource requested or is unwilling to disclose if it exists. Could indicate a defect in the client program or data which is no longer accessible.",
                        "schema": {
                            "description": "Defines an error that occurred.",
                            "type": "object",
                            "required": [
                                "code",
                                "message"
                            ],
                            "properties": {
                                "code": {
                                    "description": "A short mnemonic reference code for the error.",
                                    "type": "string",
                                    "maxLength": 40
                                },
                                "message": {
                                    "description": "A human readable description of the error.",
                                    "type": "string"
                                }
                            }
                        },
                        "headers": {
                            "VND.com.blackrock.Request-ID": {
                                "type": "string",
                                "format": "UUID",
                                "description": "The unique identifier assigned by the client to the request that originated this response."
                            },
                            "VND.com.blackrock.Response-ID": {
                                "type": "string",
                                "format": "UUID",
                                "description": "A Unique Identifier for this response."
                            },
                            "VND.com.blackrock.Response-Timestamp": {
                                "type": "string",
                                "format": "date-time",
                                "description": "Timestamp assigned to this response, in \"HTTP-date\" format as defined by RFC 7231."
                            }
                        }
                    }
                },
                "x-access-type": "WRITE",
                "x-quota-limit": 100
            }
        },
        "/researchNotes/{id}": {
            "get": {
                "description": "Retrieves a published investment research note for a specified note id",
                "summary": "Gets a research note",
                "operationId": "ResearchNoteAPI_GetResearchNote",
                "parameters": [
                    {
                        "type": "string",
                        "format": "UUID",
                        "description": "A unique identifier for this request.",
                        "name": "VND.com.blackrock.Request-ID",
                        "in": "header",
                        "required": true
                    },
                    {
                        "type": "string",
                        "format": "date-time",
                        "description": "Timestamp assigned to this request at origin, in \"HTTP-date\" format as defined by RFC 7231.",
                        "name": "VND.com.blackrock.Origin-Timestamp",
                        "in": "header",
                        "required": true
                    },
                    {
                        "type": "string",
                        "description": "Research Id",
                        "name": "id",
                        "in": "path",
                        "required": true
                    }
                ],
                "responses": {
                    "200": {
                        "description": "A successful response.",
                        "schema": {
                            "$ref": "#/definitions/v1ResearchNote"
                        }
                    },
                    "400": {
                        "description": "Aladdin® will not process the request due to an apparent client error.",
                        "schema": {
                            "description": "Defines an error that occurred.",
                            "type": "object",
                            "required": [
                                "code",
                                "message"
                            ],
                            "properties": {
                                "code": {
                                    "description": "A short mnemonic reference code for the error.",
                                    "type": "string",
                                    "maxLength": 40
                                },
                                "message": {
                                    "description": "A human readable description of the error.",
                                    "type": "string"
                                }
                            }
                        },
                        "headers": {
                            "VND.com.blackrock.Request-ID": {
                                "type": "string",
                                "format": "UUID",
                                "description": "The unique identifier assigned by the client to the request that originated this response."
                            },
                            "VND.com.blackrock.Response-ID": {
                                "type": "string",
                                "format": "UUID",
                                "description": "A Unique Identifier for this response."
                            },
                            "VND.com.blackrock.Response-Timestamp": {
                                "type": "string",
                                "format": "date-time",
                                "description": "Timestamp assigned to this response, in \"HTTP-date\" format as defined by RFC 7231."
                            }
                        }
                    },
                    "401": {
                        "description": "Aladdin® will not process the request as the necessary credentials were not provided or were invalid.",
                        "schema": {
                            "description": "Defines an error that occurred.",
                            "type": "object",
                            "required": [
                                "code",
                                "message"
                            ],
                            "properties": {
                                "code": {
                                    "description": "A short mnemonic reference code for the error.",
                                    "type": "string",
                                    "maxLength": 40
                                },
                                "message": {
                                    "description": "A human readable description of the error.",
                                    "type": "string"
                                }
                            }
                        },
                        "headers": {
                            "VND.com.blackrock.Request-ID": {
                                "type": "string",
                                "format": "UUID",
                                "description": "The unique identifier assigned by the client to the request that originated this response."
                            },
                            "VND.com.blackrock.Response-ID": {
                                "type": "string",
                                "format": "UUID",
                                "description": "A Unique Identifier for this response."
                            },
                            "VND.com.blackrock.Response-Timestamp": {
                                "type": "string",
                                "format": "date-time",
                                "description": "Timestamp assigned to this response, in \"HTTP-date\" format as defined by RFC 7231."
                            }
                        }
                    },
                    "403": {
                        "description": "Aladdin® understood the request but is refusing to authorize it.",
                        "schema": {
                            "description": "Defines an error that occurred.",
                            "type": "object",
                            "required": [
                                "code",
                                "message"
                            ],
                            "properties": {
                                "code": {
                                    "description": "A short mnemonic reference code for the error.",
                                    "type": "string",
                                    "maxLength": 40
                                },
                                "message": {
                                    "description": "A human readable description of the error.",
                                    "type": "string"
                                }
                            }
                        },
                        "headers": {
                            "VND.com.blackrock.Request-ID": {
                                "type": "string",
                                "format": "UUID",
                                "description": "The unique identifier assigned by the client to the request that originated this response."
                            },
                            "VND.com.blackrock.Response-ID": {
                                "type": "string",
                                "format": "UUID",
                                "description": "A Unique Identifier for this response."
                            },
                            "VND.com.blackrock.Response-Timestamp": {
                                "type": "string",
                                "format": "date-time",
                                "description": "Timestamp assigned to this response, in \"HTTP-date\" format as defined by RFC 7231."
                            }
                        }
                    },
                    "404": {
                        "description": "Aladdin® did not find the resource requested or is unwilling to disclose if it exists. Could indicate a defect in the client program or data which is no longer accessible.",
                        "schema": {
                            "description": "Defines an error that occurred.",
                            "type": "object",
                            "required": [
                                "code",
                                "message"
                            ],
                            "properties": {
                                "code": {
                                    "description": "A short mnemonic reference code for the error.",
                                    "type": "string",
                                    "maxLength": 40
                                },
                                "message": {
                                    "description": "A human readable description of the error.",
                                    "type": "string"
                                }
                            }
                        },
                        "headers": {
                            "VND.com.blackrock.Request-ID": {
                                "type": "string",
                                "format": "UUID",
                                "description": "The unique identifier assigned by the client to the request that originated this response."
                            },
                            "VND.com.blackrock.Response-ID": {
                                "type": "string",
                                "format": "UUID",
                                "description": "A Unique Identifier for this response."
                            },
                            "VND.com.blackrock.Response-Timestamp": {
                                "type": "string",
                                "format": "date-time",
                                "description": "Timestamp assigned to this response, in \"HTTP-date\" format as defined by RFC 7231."
                            }
                        }
                    }
                },
                "x-access-type": "READ",
                "x-quota-limit": 100
            },
            "delete": {
                "description": "Deletes a published research note",
                "summary": "Deletes a research note",
                "operationId": "ResearchNoteAPI_DeleteResearchNote",
                "parameters": [
                    {
                        "type": "string",
                        "format": "UUID",
                        "description": "A unique identifier for this request.",
                        "name": "VND.com.blackrock.Request-ID",
                        "in": "header",
                        "required": true
                    },
                    {
                        "type": "string",
                        "format": "date-time",
                        "description": "Timestamp assigned to this request at origin, in \"HTTP-date\" format as defined by RFC 7231.",
                        "name": "VND.com.blackrock.Origin-Timestamp",
                        "in": "header",
                        "required": true
                    },
                    {
                        "type": "string",
                        "description": "Name of the Research",
                        "name": "id",
                        "in": "path",
                        "required": true
                    }
                ],
                "responses": {
                    "200": {
                        "description": "A successful response.",
                        "schema": {}
                    },
                    "400": {
                        "description": "Aladdin® will not process the request due to an apparent client error.",
                        "schema": {
                            "description": "Defines an error that occurred.",
                            "type": "object",
                            "required": [
                                "code",
                                "message"
                            ],
                            "properties": {
                                "code": {
                                    "description": "A short mnemonic reference code for the error.",
                                    "type": "string",
                                    "maxLength": 40
                                },
                                "message": {
                                    "description": "A human readable description of the error.",
                                    "type": "string"
                                }
                            }
                        },
                        "headers": {
                            "VND.com.blackrock.Request-ID": {
                                "type": "string",
                                "format": "UUID",
                                "description": "The unique identifier assigned by the client to the request that originated this response."
                            },
                            "VND.com.blackrock.Response-ID": {
                                "type": "string",
                                "format": "UUID",
                                "description": "A Unique Identifier for this response."
                            },
                            "VND.com.blackrock.Response-Timestamp": {
                                "type": "string",
                                "format": "date-time",
                                "description": "Timestamp assigned to this response, in \"HTTP-date\" format as defined by RFC 7231."
                            }
                        }
                    },
                    "401": {
                        "description": "Aladdin® will not process the request as the necessary credentials were not provided or were invalid.",
                        "schema": {
                            "description": "Defines an error that occurred.",
                            "type": "object",
                            "required": [
                                "code",
                                "message"
                            ],
                            "properties": {
                                "code": {
                                    "description": "A short mnemonic reference code for the error.",
                                    "type": "string",
                                    "maxLength": 40
                                },
                                "message": {
                                    "description": "A human readable description of the error.",
                                    "type": "string"
                                }
                            }
                        },
                        "headers": {
                            "VND.com.blackrock.Request-ID": {
                                "type": "string",
                                "format": "UUID",
                                "description": "The unique identifier assigned by the client to the request that originated this response."
                            },
                            "VND.com.blackrock.Response-ID": {
                                "type": "string",
                                "format": "UUID",
                                "description": "A Unique Identifier for this response."
                            },
                            "VND.com.blackrock.Response-Timestamp": {
                                "type": "string",
                                "format": "date-time",
                                "description": "Timestamp assigned to this response, in \"HTTP-date\" format as defined by RFC 7231."
                            }
                        }
                    },
                    "403": {
                        "description": "Aladdin® understood the request but is refusing to authorize it.",
                        "schema": {
                            "description": "Defines an error that occurred.",
                            "type": "object",
                            "required": [
                                "code",
                                "message"
                            ],
                            "properties": {
                                "code": {
                                    "description": "A short mnemonic reference code for the error.",
                                    "type": "string",
                                    "maxLength": 40
                                },
                                "message": {
                                    "description": "A human readable description of the error.",
                                    "type": "string"
                                }
                            }
                        },
                        "headers": {
                            "VND.com.blackrock.Request-ID": {
                                "type": "string",
                                "format": "UUID",
                                "description": "The unique identifier assigned by the client to the request that originated this response."
                            },
                            "VND.com.blackrock.Response-ID": {
                                "type": "string",
                                "format": "UUID",
                                "description": "A Unique Identifier for this response."
                            },
                            "VND.com.blackrock.Response-Timestamp": {
                                "type": "string",
                                "format": "date-time",
                                "description": "Timestamp assigned to this response, in \"HTTP-date\" format as defined by RFC 7231."
                            }
                        }
                    },
                    "404": {
                        "description": "Aladdin® did not find the resource requested or is unwilling to disclose if it exists. Could indicate a defect in the client program or data which is no longer accessible.",
                        "schema": {
                            "description": "Defines an error that occurred.",
                            "type": "object",
                            "required": [
                                "code",
                                "message"
                            ],
                            "properties": {
                                "code": {
                                    "description": "A short mnemonic reference code for the error.",
                                    "type": "string",
                                    "maxLength": 40
                                },
                                "message": {
                                    "description": "A human readable description of the error.",
                                    "type": "string"
                                }
                            }
                        },
                        "headers": {
                            "VND.com.blackrock.Request-ID": {
                                "type": "string",
                                "format": "UUID",
                                "description": "The unique identifier assigned by the client to the request that originated this response."
                            },
                            "VND.com.blackrock.Response-ID": {
                                "type": "string",
                                "format": "UUID",
                                "description": "A Unique Identifier for this response."
                            },
                            "VND.com.blackrock.Response-Timestamp": {
                                "type": "string",
                                "format": "date-time",
                                "description": "Timestamp assigned to this response, in \"HTTP-date\" format as defined by RFC 7231."
                            }
                        }
                    }
                },
                "x-access-type": "WRITE",
                "x-quota-limit": 100
            }
        },
        "/researchNotes/{researchNote.id}": {
            "patch": {
                "description": "Updates a published research note",
                "summary": "Updates a research note",
                "operationId": "ResearchNoteAPI_UpdateResearchNote",
                "parameters": [
                    {
                        "type": "string",
                        "format": "UUID",
                        "description": "A unique identifier for this request.",
                        "name": "VND.com.blackrock.Request-ID",
                        "in": "header",
                        "required": true
                    },
                    {
                        "type": "string",
                        "format": "date-time",
                        "description": "Timestamp assigned to this request at origin, in \"HTTP-date\" format as defined by RFC 7231.",
                        "name": "VND.com.blackrock.Origin-Timestamp",
                        "in": "header",
                        "required": true
                    },
                    {
                        "type": "string",
                        "description": "ID describes the computer or human assigned resource identifier.\nThe research note id.",
                        "name": "researchNote.id",
                        "in": "path",
                        "required": true
                    },
                    {
                        "description": "research to update.",
                        "name": "body",
                        "in": "body",
                        "required": true,
                        "schema": {
                            "$ref": "#/definitions/v1ResearchNote"
                        }
                    },
                    {
                        "type": "string",
                        "description": "List of fields to be updated.",
                        "name": "updateMask",
                        "in": "query"
                    }
                ],
                "responses": {
                    "200": {
                        "description": "A successful response.",
                        "schema": {
                            "$ref": "#/definitions/v1ResearchNote"
                        }
                    },
                    "400": {
                        "description": "Aladdin® will not process the request due to an apparent client error.",
                        "schema": {
                            "description": "Defines an error that occurred.",
                            "type": "object",
                            "required": [
                                "code",
                                "message"
                            ],
                            "properties": {
                                "code": {
                                    "description": "A short mnemonic reference code for the error.",
                                    "type": "string",
                                    "maxLength": 40
                                },
                                "message": {
                                    "description": "A human readable description of the error.",
                                    "type": "string"
                                }
                            }
                        },
                        "headers": {
                            "VND.com.blackrock.Request-ID": {
                                "type": "string",
                                "format": "UUID",
                                "description": "The unique identifier assigned by the client to the request that originated this response."
                            },
                            "VND.com.blackrock.Response-ID": {
                                "type": "string",
                                "format": "UUID",
                                "description": "A Unique Identifier for this response."
                            },
                            "VND.com.blackrock.Response-Timestamp": {
                                "type": "string",
                                "format": "date-time",
                                "description": "Timestamp assigned to this response, in \"HTTP-date\" format as defined by RFC 7231."
                            }
                        }
                    },
                    "401": {
                        "description": "Aladdin® will not process the request as the necessary credentials were not provided or were invalid.",
                        "schema": {
                            "description": "Defines an error that occurred.",
                            "type": "object",
                            "required": [
                                "code",
                                "message"
                            ],
                            "properties": {
                                "code": {
                                    "description": "A short mnemonic reference code for the error.",
                                    "type": "string",
                                    "maxLength": 40
                                },
                                "message": {
                                    "description": "A human readable description of the error.",
                                    "type": "string"
                                }
                            }
                        },
                        "headers": {
                            "VND.com.blackrock.Request-ID": {
                                "type": "string",
                                "format": "UUID",
                                "description": "The unique identifier assigned by the client to the request that originated this response."
                            },
                            "VND.com.blackrock.Response-ID": {
                                "type": "string",
                                "format": "UUID",
                                "description": "A Unique Identifier for this response."
                            },
                            "VND.com.blackrock.Response-Timestamp": {
                                "type": "string",
                                "format": "date-time",
                                "description": "Timestamp assigned to this response, in \"HTTP-date\" format as defined by RFC 7231."
                            }
                        }
                    },
                    "403": {
                        "description": "Aladdin® understood the request but is refusing to authorize it.",
                        "schema": {
                            "description": "Defines an error that occurred.",
                            "type": "object",
                            "required": [
                                "code",
                                "message"
                            ],
                            "properties": {
                                "code": {
                                    "description": "A short mnemonic reference code for the error.",
                                    "type": "string",
                                    "maxLength": 40
                                },
                                "message": {
                                    "description": "A human readable description of the error.",
                                    "type": "string"
                                }
                            }
                        },
                        "headers": {
                            "VND.com.blackrock.Request-ID": {
                                "type": "string",
                                "format": "UUID",
                                "description": "The unique identifier assigned by the client to the request that originated this response."
                            },
                            "VND.com.blackrock.Response-ID": {
                                "type": "string",
                                "format": "UUID",
                                "description": "A Unique Identifier for this response."
                            },
                            "VND.com.blackrock.Response-Timestamp": {
                                "type": "string",
                                "format": "date-time",
                                "description": "Timestamp assigned to this response, in \"HTTP-date\" format as defined by RFC 7231."
                            }
                        }
                    },
                    "404": {
                        "description": "Aladdin® did not find the resource requested or is unwilling to disclose if it exists. Could indicate a defect in the client program or data which is no longer accessible.",
                        "schema": {
                            "description": "Defines an error that occurred.",
                            "type": "object",
                            "required": [
                                "code",
                                "message"
                            ],
                            "properties": {
                                "code": {
                                    "description": "A short mnemonic reference code for the error.",
                                    "type": "string",
                                    "maxLength": 40
                                },
                                "message": {
                                    "description": "A human readable description of the error.",
                                    "type": "string"
                                }
                            }
                        },
                        "headers": {
                            "VND.com.blackrock.Request-ID": {
                                "type": "string",
                                "format": "UUID",
                                "description": "The unique identifier assigned by the client to the request that originated this response."
                            },
                            "VND.com.blackrock.Response-ID": {
                                "type": "string",
                                "format": "UUID",
                                "description": "A Unique Identifier for this response."
                            },
                            "VND.com.blackrock.Response-Timestamp": {
                                "type": "string",
                                "format": "date-time",
                                "description": "Timestamp assigned to this response, in \"HTTP-date\" format as defined by RFC 7231."
                            }
                        }
                    }
                },
                "x-access-type": "WRITE",
                "x-quota-limit": 100
            }
        },
        "/researchNotes:search": {
            "get": {
                "description": "Retrieves published research notes that match a specified set of research note attribute criteria (author, department, security, issuer, industry sector, etc.)",
                "summary": "Search research notes",
                "operationId": "ResearchNoteAPI_SearchResearchNotes",
                "parameters": [
                    {
                        "type": "string",
                        "format": "UUID",
                        "description": "A unique identifier for this request.",
                        "name": "VND.com.blackrock.Request-ID",
                        "in": "header",
                        "required": true
                    },
                    {
                        "type": "string",
                        "format": "date-time",
                        "description": "Timestamp assigned to this request at origin, in \"HTTP-date\" format as defined by RFC 7231.",
                        "name": "VND.com.blackrock.Origin-Timestamp",
                        "in": "header",
                        "required": true
                    },
                    {
                        "type": "array",
                        "items": {
                            "type": "string"
                        },
                        "collectionFormat": "multi",
                        "description": "Specifies the filter criteria, please refer to ResearchNote message for valid criteria target field name\nThe supported syntax (for now): \nnote.[target field]:[term] Eg: note.author:\"user\"\n[term] Eg: Technology (Matches anything containing Technology anywhere). Multiple criteria can also be joined by AND and OR logic operator\nOther supported logic operator includes ! means not equal, IN for a list of value terms, etc.\ne.g. note.author:\"user\" AND (note.entities.asset_id:\"123456789\" OR note.entities.issuer:\"*ABC*\") , etc.\nValid field name could be referered in the ResearchNote message type\n(-- aip.dev/beta-blocker: Further refactoring/change is needed when the search/filtering standards are finalized --)\n(-- api-linter: core::0132::request-unknown-fields=disabled\n    aip.dev/not-precedent: We really need this field because it is already being used in prod. --)",
                        "name": "filterCriteria",
                        "in": "query"
                    },
                    {
                        "type": "string",
                        "description": "Sorts the response with ascending or descending order based on specific field. Default as asc. e.g. \"note.publish_time desc, note.author\".",
                        "name": "orderBy",
                        "in": "query"
                    },
                    {
                        "type": "integer",
                        "format": "int32",
                        "description": "The maximum number of research notes to return. The service may\nreturn fewer than this value. If unspecified, at most 10\nnote will be returned.",
                        "name": "pageSize",
                        "in": "query"
                    },
                    {
                        "type": "string",
                        "description": "A page token, received from a previous 'SearchResearchNotes' call.\nProvide this to retrieve the subsequent page.\n\nWhen paginating, all other parameters provided to\n'SearchResearchNotes' must match the call that provided the page\ntoken.",
                        "name": "pageToken",
                        "in": "query"
                    },
                    {
                        "type": "array",
                        "items": {
                            "type": "string"
                        },
                        "collectionFormat": "multi",
                        "description": "Used to provide with facet search capabilities by simply specifiying the fields to be used as base\nand by consequence, returned with an array for each of the specified fields and it's terms and\nmatches for each of the entries.",
                        "name": "facetFields",
                        "in": "query"
                    },
                    {
                        "type": "array",
                        "items": {
                            "type": "string"
                        },
                        "collectionFormat": "multi",
                        "description": "When the field list is provided, only retrieve specified fields.\n(-- api-linter: core::0132::request-unknown-fields=disabled\n aip.dev/not-precedent: We need to do this because field list is required for security reasons --).",
                        "name": "fieldLists",
                        "in": "query"
                    }
                ],
                "responses": {
                    "200": {
                        "description": "A successful response.",
                        "schema": {
                            "$ref": "#/definitions/v1SearchResearchNotesResponse"
                        }
                    },
                    "400": {
                        "description": "Aladdin® will not process the request due to an apparent client error.",
                        "schema": {
                            "description": "Defines an error that occurred.",
                            "type": "object",
                            "required": [
                                "code",
                                "message"
                            ],
                            "properties": {
                                "code": {
                                    "description": "A short mnemonic reference code for the error.",
                                    "type": "string",
                                    "maxLength": 40
                                },
                                "message": {
                                    "description": "A human readable description of the error.",
                                    "type": "string"
                                }
                            }
                        },
                        "headers": {
                            "VND.com.blackrock.Request-ID": {
                                "type": "string",
                                "format": "UUID",
                                "description": "The unique identifier assigned by the client to the request that originated this response."
                            },
                            "VND.com.blackrock.Response-ID": {
                                "type": "string",
                                "format": "UUID",
                                "description": "A Unique Identifier for this response."
                            },
                            "VND.com.blackrock.Response-Timestamp": {
                                "type": "string",
                                "format": "date-time",
                                "description": "Timestamp assigned to this response, in \"HTTP-date\" format as defined by RFC 7231."
                            }
                        }
                    },
                    "401": {
                        "description": "Aladdin® will not process the request as the necessary credentials were not provided or were invalid.",
                        "schema": {
                            "description": "Defines an error that occurred.",
                            "type": "object",
                            "required": [
                                "code",
                                "message"
                            ],
                            "properties": {
                                "code": {
                                    "description": "A short mnemonic reference code for the error.",
                                    "type": "string",
                                    "maxLength": 40
                                },
                                "message": {
                                    "description": "A human readable description of the error.",
                                    "type": "string"
                                }
                            }
                        },
                        "headers": {
                            "VND.com.blackrock.Request-ID": {
                                "type": "string",
                                "format": "UUID",
                                "description": "The unique identifier assigned by the client to the request that originated this response."
                            },
                            "VND.com.blackrock.Response-ID": {
                                "type": "string",
                                "format": "UUID",
                                "description": "A Unique Identifier for this response."
                            },
                            "VND.com.blackrock.Response-Timestamp": {
                                "type": "string",
                                "format": "date-time",
                                "description": "Timestamp assigned to this response, in \"HTTP-date\" format as defined by RFC 7231."
                            }
                        }
                    },
                    "403": {
                        "description": "Aladdin® understood the request but is refusing to authorize it.",
                        "schema": {
                            "description": "Defines an error that occurred.",
                            "type": "object",
                            "required": [
                                "code",
                                "message"
                            ],
                            "properties": {
                                "code": {
                                    "description": "A short mnemonic reference code for the error.",
                                    "type": "string",
                                    "maxLength": 40
                                },
                                "message": {
                                    "description": "A human readable description of the error.",
                                    "type": "string"
                                }
                            }
                        },
                        "headers": {
                            "VND.com.blackrock.Request-ID": {
                                "type": "string",
                                "format": "UUID",
                                "description": "The unique identifier assigned by the client to the request that originated this response."
                            },
                            "VND.com.blackrock.Response-ID": {
                                "type": "string",
                                "format": "UUID",
                                "description": "A Unique Identifier for this response."
                            },
                            "VND.com.blackrock.Response-Timestamp": {
                                "type": "string",
                                "format": "date-time",
                                "description": "Timestamp assigned to this response, in \"HTTP-date\" format as defined by RFC 7231."
                            }
                        }
                    },
                    "404": {
                        "description": "Aladdin® did not find the resource requested or is unwilling to disclose if it exists. Could indicate a defect in the client program or data which is no longer accessible.",
                        "schema": {
                            "description": "Defines an error that occurred.",
                            "type": "object",
                            "required": [
                                "code",
                                "message"
                            ],
                            "properties": {
                                "code": {
                                    "description": "A short mnemonic reference code for the error.",
                                    "type": "string",
                                    "maxLength": 40
                                },
                                "message": {
                                    "description": "A human readable description of the error.",
                                    "type": "string"
                                }
                            }
                        },
                        "headers": {
                            "VND.com.blackrock.Request-ID": {
                                "type": "string",
                                "format": "UUID",
                                "description": "The unique identifier assigned by the client to the request that originated this response."
                            },
                            "VND.com.blackrock.Response-ID": {
                                "type": "string",
                                "format": "UUID",
                                "description": "A Unique Identifier for this response."
                            },
                            "VND.com.blackrock.Response-Timestamp": {
                                "type": "string",
                                "format": "date-time",
                                "description": "Timestamp assigned to this response, in \"HTTP-date\" format as defined by RFC 7231."
                            }
                        }
                    }
                },
                "x-access-type": "READ",
                "x-quota-limit": 100
            }
        },
        "/userPreferences": {
            "get": {
                "description": "Retrieves user preferences\n(-- api-linter: core::0131::http-uri-id=disabled\n    aip.dev/not-precedent: We need to do this passing the user id could open a security gap. --)",
                "summary": "Gets a user's preferences",
                "operationId": "ResearchNoteAPI_GetUserPreferences",
                "parameters": [
                    {
                        "type": "string",
                        "format": "UUID",
                        "description": "A unique identifier for this request.",
                        "name": "VND.com.blackrock.Request-ID",
                        "in": "header",
                        "required": true
                    },
                    {
                        "type": "string",
                        "format": "date-time",
                        "description": "Timestamp assigned to this request at origin, in \"HTTP-date\" format as defined by RFC 7231.",
                        "name": "VND.com.blackrock.Origin-Timestamp",
                        "in": "header",
                        "required": true
                    }
                ],
                "responses": {
                    "200": {
                        "description": "A successful response.",
                        "schema": {
                            "$ref": "#/definitions/v1UserPreferences"
                        }
                    },
                    "400": {
                        "description": "Aladdin® will not process the request due to an apparent client error.",
                        "schema": {
                            "description": "Defines an error that occurred.",
                            "type": "object",
                            "required": [
                                "code",
                                "message"
                            ],
                            "properties": {
                                "code": {
                                    "description": "A short mnemonic reference code for the error.",
                                    "type": "string",
                                    "maxLength": 40
                                },
                                "message": {
                                    "description": "A human readable description of the error.",
                                    "type": "string"
                                }
                            }
                        },
                        "headers": {
                            "VND.com.blackrock.Request-ID": {
                                "type": "string",
                                "format": "UUID",
                                "description": "The unique identifier assigned by the client to the request that originated this response."
                            },
                            "VND.com.blackrock.Response-ID": {
                                "type": "string",
                                "format": "UUID",
                                "description": "A Unique Identifier for this response."
                            },
                            "VND.com.blackrock.Response-Timestamp": {
                                "type": "string",
                                "format": "date-time",
                                "description": "Timestamp assigned to this response, in \"HTTP-date\" format as defined by RFC 7231."
                            }
                        }
                    },
                    "401": {
                        "description": "Aladdin® will not process the request as the necessary credentials were not provided or were invalid.",
                        "schema": {
                            "description": "Defines an error that occurred.",
                            "type": "object",
                            "required": [
                                "code",
                                "message"
                            ],
                            "properties": {
                                "code": {
                                    "description": "A short mnemonic reference code for the error.",
                                    "type": "string",
                                    "maxLength": 40
                                },
                                "message": {
                                    "description": "A human readable description of the error.",
                                    "type": "string"
                                }
                            }
                        },
                        "headers": {
                            "VND.com.blackrock.Request-ID": {
                                "type": "string",
                                "format": "UUID",
                                "description": "The unique identifier assigned by the client to the request that originated this response."
                            },
                            "VND.com.blackrock.Response-ID": {
                                "type": "string",
                                "format": "UUID",
                                "description": "A Unique Identifier for this response."
                            },
                            "VND.com.blackrock.Response-Timestamp": {
                                "type": "string",
                                "format": "date-time",
                                "description": "Timestamp assigned to this response, in \"HTTP-date\" format as defined by RFC 7231."
                            }
                        }
                    },
                    "403": {
                        "description": "Aladdin® understood the request but is refusing to authorize it.",
                        "schema": {
                            "description": "Defines an error that occurred.",
                            "type": "object",
                            "required": [
                                "code",
                                "message"
                            ],
                            "properties": {
                                "code": {
                                    "description": "A short mnemonic reference code for the error.",
                                    "type": "string",
                                    "maxLength": 40
                                },
                                "message": {
                                    "description": "A human readable description of the error.",
                                    "type": "string"
                                }
                            }
                        },
                        "headers": {
                            "VND.com.blackrock.Request-ID": {
                                "type": "string",
                                "format": "UUID",
                                "description": "The unique identifier assigned by the client to the request that originated this response."
                            },
                            "VND.com.blackrock.Response-ID": {
                                "type": "string",
                                "format": "UUID",
                                "description": "A Unique Identifier for this response."
                            },
                            "VND.com.blackrock.Response-Timestamp": {
                                "type": "string",
                                "format": "date-time",
                                "description": "Timestamp assigned to this response, in \"HTTP-date\" format as defined by RFC 7231."
                            }
                        }
                    },
                    "404": {
                        "description": "Aladdin® did not find the resource requested or is unwilling to disclose if it exists. Could indicate a defect in the client program or data which is no longer accessible.",
                        "schema": {
                            "description": "Defines an error that occurred.",
                            "type": "object",
                            "required": [
                                "code",
                                "message"
                            ],
                            "properties": {
                                "code": {
                                    "description": "A short mnemonic reference code for the error.",
                                    "type": "string",
                                    "maxLength": 40
                                },
                                "message": {
                                    "description": "A human readable description of the error.",
                                    "type": "string"
                                }
                            }
                        },
                        "headers": {
                            "VND.com.blackrock.Request-ID": {
                                "type": "string",
                                "format": "UUID",
                                "description": "The unique identifier assigned by the client to the request that originated this response."
                            },
                            "VND.com.blackrock.Response-ID": {
                                "type": "string",
                                "format": "UUID",
                                "description": "A Unique Identifier for this response."
                            },
                            "VND.com.blackrock.Response-Timestamp": {
                                "type": "string",
                                "format": "date-time",
                                "description": "Timestamp assigned to this response, in \"HTTP-date\" format as defined by RFC 7231."
                            }
                        }
                    }
                },
                "x-access-type": "READ",
                "x-quota-limit": 100
            }
        }
    },
    "definitions": {
        "Any": {
            "description": "`Any` contains an arbitrary serialized message along with a\nURL that describes the type of the serialized message",
            "type": "object",
            "properties": {
                "@type": {
                    "description": "A URL/resource name that uniquely identifies the type of the serialized message.",
                    "type": "string"
                }
            }
        },
        "rpcStatus": {
            "type": "object",
            "properties": {
                "code": {
                    "type": "integer",
                    "format": "int32"
                },
                "message": {
                    "type": "string"
                },
                "details": {
                    "type": "array",
                    "items": {
                        "$ref": "#/definitions/Any"
                    }
                }
            }
        },
        "typesEntityId": {
            "type": "object",
            "title": "The entity Id",
            "properties": {
                "issuer": {
                    "type": "string",
                    "title": "Issuer"
                },
                "assetId": {
                    "type": "string",
                    "title": "Asset id for security"
                },
                "investmentStrategyId": {
                    "type": "string",
                    "title": "Investment strategy id"
                }
            }
        },
        "v1ExpiringPermissionGroup": {
            "type": "object",
            "title": "Expiring permission group",
            "properties": {
                "permissionGroup": {
                    "type": "string",
                    "title": "permission group\n(-- aip.dev/beta-blocker: refactor to use permission common resource when it's ready --)"
                },
                "timeUnit": {
                    "title": "time unit",
                    "$ref": "#/definitions/v1ExpiringPermissionTimeUnit"
                },
                "timeSpan": {
                    "type": "integer",
                    "format": "int32",
                    "title": "time span"
                }
            }
        },
        "v1ExpiringPermissionTimeUnit": {
            "description": "- EXPIRING_PERMISSION_TIME_UNIT_UNSPECIFIED: Unspecified\n - EXPIRING_PERMISSION_TIME_UNIT_DAYS: Days\n - EXPIRING_PERMISSION_TIME_UNIT_WEEKS: Weeks\n - EXPIRING_PERMISSION_TIME_UNIT_MONTHS: Months\n - EXPIRING_PERMISSION_TIME_UNIT_FOREVER: Forever",
            "type": "string",
            "title": "Expiring Permission Time Unit enums",
            "default": "EXPIRING_PERMISSION_TIME_UNIT_UNSPECIFIED",
            "enum": [
                "EXPIRING_PERMISSION_TIME_UNIT_UNSPECIFIED",
                "EXPIRING_PERMISSION_TIME_UNIT_DAYS",
                "EXPIRING_PERMISSION_TIME_UNIT_WEEKS",
                "EXPIRING_PERMISSION_TIME_UNIT_MONTHS",
                "EXPIRING_PERMISSION_TIME_UNIT_FOREVER"
            ]
        },
        "v1InvestmentStewardshipAssessment": {
            "description": "- INVESTMENT_STEWARDSHIP_ASSESSMENT_UNSPECIFIED: Unspecified or N/A\n - INVESTMENT_STEWARDSHIP_ASSESSMENT_COMPLETELY_SATISFIED: Completely satisfied\n - INVESTMENT_STEWARDSHIP_ASSESSMENT_MOSTLY_SATISFIED: Mostly satisfied\n - INVESTMENT_STEWARDSHIP_ASSESSMENT_NEUTRAL: Neither satisfied nor unsatisfied\n - INVESTMENT_STEWARDSHIP_ASSESSMENT_MOSTLY_UNSATISFIED: Mostly unsatisfied\n - INVESTMENT_STEWARDSHIP_ASSESSMENT_COMPLETELY_UNSATISFIED: Not at all satisfied",
            "type": "string",
            "title": "Investment stewardship assessment enums",
            "default": "INVESTMENT_STEWARDSHIP_ASSESSMENT_UNSPECIFIED",
            "enum": [
                "INVESTMENT_STEWARDSHIP_ASSESSMENT_UNSPECIFIED",
                "INVESTMENT_STEWARDSHIP_ASSESSMENT_COMPLETELY_SATISFIED",
                "INVESTMENT_STEWARDSHIP_ASSESSMENT_MOSTLY_SATISFIED",
                "INVESTMENT_STEWARDSHIP_ASSESSMENT_NEUTRAL",
                "INVESTMENT_STEWARDSHIP_ASSESSMENT_MOSTLY_UNSATISFIED",
                "INVESTMENT_STEWARDSHIP_ASSESSMENT_COMPLETELY_UNSATISFIED"
            ]
        },
        "v1InvestmentStewardshipDetail": {
            "type": "object",
            "title": "Investment Stewardship note details",
            "properties": {
                "engagementType": {
                    "description": "Engagement type.",
                    "$ref": "#/definitions/v1InvestmentStewardshipEngagement"
                },
                "initiator": {
                    "description": "Initiated by.",
                    "$ref": "#/definitions/v1InvestmentStewardshipInitiator"
                },
                "format": {
                    "description": "Format.",
                    "$ref": "#/definitions/v1InvestmentStewardshipFormat"
                },
                "score": {
                    "description": "Score.",
                    "$ref": "#/definitions/v1InvestmentStewardshipScore"
                },
                "engagementDate": {
                    "description": "Engagement date.",
                    "type": "string",
                    "format": "date"
                },
                "externalAttendees": {
                    "description": "External attendees.",
                    "type": "array",
                    "items": {
                        "type": "string"
                    }
                },
                "internalAttendees": {
                    "description": "Internal attendees.",
                    "type": "array",
                    "items": {
                        "type": "string"
                    }
                },
                "reporting": {
                    "description": "Reporting.",
                    "type": "boolean"
                },
                "highProfile": {
                    "description": "High profile.",
                    "type": "boolean"
                },
                "topics": {
                    "description": "Topics text.",
                    "type": "array",
                    "items": {
                        "$ref": "#/definitions/v1InvestmentStewardshipTopicDetails"
                    }
                },
                "fixedKeywords": {
                    "type": "array",
                    "title": "Fixed keywords, which is specific to investment stewardship type of note that provides\na fixed list of keyword tags for certain common topic/tags used in investment stewardship",
                    "items": {
                        "$ref": "#/definitions/v1InvestmentStewardshipFixedKeyword"
                    }
                },
                "clientNote": {
                    "type": "string",
                    "title": "In addition to the general note content, the investment stewardship note provides one additional \nnote field, Client Note, for user to record client's feedback"
                }
            }
        },
        "v1InvestmentStewardshipEngagement": {
            "description": "- INVESTMENT_STEWARDSHIP_ENGAGEMENT_UNSPECIFIED: Unspecified\n - INVESTMENT_STEWARDSHIP_ENGAGEMENT_GENERAL_THEMATIC: General/Thematic\n - INVESTMENT_STEWARDSHIP_ENGAGEMENT_PREVOTE_CLARIFICATION: Pre-Vote Clarification\n - INVESTMENT_STEWARDSHIP_ENGAGEMENT_POSTVOTE_RATIONALE_EXPLANATION: Post-Vote Rationale Explanation",
            "type": "string",
            "title": "Investment stewardship engagement type field",
            "default": "INVESTMENT_STEWARDSHIP_ENGAGEMENT_UNSPECIFIED",
            "enum": [
                "INVESTMENT_STEWARDSHIP_ENGAGEMENT_UNSPECIFIED",
                "INVESTMENT_STEWARDSHIP_ENGAGEMENT_GENERAL_THEMATIC",
                "INVESTMENT_STEWARDSHIP_ENGAGEMENT_PREVOTE_CLARIFICATION",
                "INVESTMENT_STEWARDSHIP_ENGAGEMENT_POSTVOTE_RATIONALE_EXPLANATION"
            ]
        },
        "v1InvestmentStewardshipFixedKeyword": {
            "description": "- INVESTMENT_STEWARDSHIP_FIXED_KEYWORD_UNSPECIFIED: Unspecified\n - INVESTMENT_STEWARDSHIP_FIXED_KEYWORD_ACTIVIST: Activist\n - INVESTMENT_STEWARDSHIP_FIXED_KEYWORD_BOARD_MEMBER: Board Member\n - INVESTMENT_STEWARDSHIP_FIXED_KEYWORD_BOARD_SECRETARY: Board Secretary\n - INVESTMENT_STEWARDSHIP_FIXED_KEYWORD_BOARD_DIVERSITY: Board Diversity\n - INVESTMENT_STEWARDSHIP_FIXED_KEYWORD_CEO: CEO\n - INVESTMENT_STEWARDSHIP_FIXED_KEYWORD_CHAIRMAN: Chairman\n - INVESTMENT_STEWARDSHIP_FIXED_KEYWORD_CYBER_SECURITY: Cybersecurity\n - INVESTMENT_STEWARDSHIP_FIXED_KEYWORD_INVESTOR_RELATIONS: Investor Relations\n - INVESTMENT_STEWARDSHIP_FIXED_KEYWORD_M_AND_A: M\u0026A\n - INVESTMENT_STEWARDSHIP_FIXED_KEYWORD_OPIOIDS: Opioids\n - INVESTMENT_STEWARDSHIP_FIXED_KEYWORD_POLITICAL_ACTIVITIES: Political Activities\n - INVESTMENT_STEWARDSHIP_FIXED_KEYWORD_PROXY_ACCESS: Proxy Access\n - INVESTMENT_STEWARDSHIP_FIXED_KEYWORD_PROXY_CONTEST: Proxy Contest\n - INVESTMENT_STEWARDSHIP_FIXED_KEYWORD_PURPOSE: Purpose\n - INVESTMENT_STEWARDSHIP_FIXED_KEYWORD_SPLIT_VOTE: Split Vote\n - INVESTMENT_STEWARDSHIP_FIXED_KEYWORD_SUCCESSION_PLANNING: Succession Planning\n - INVESTMENT_STEWARDSHIP_FIXED_KEYWORD_TCFD: TCFD\n - INVESTMENT_STEWARDSHIP_FIXED_KEYWORD_UNGC: UNGC",
            "type": "string",
            "title": "Investment stewardship note fixed tag enums for certain common topics, keywords or tags, etc.\n(-- aip.dev/beta-blocker: refactor to handle the enums in a better way when it's ready --)",
            "default": "INVESTMENT_STEWARDSHIP_FIXED_KEYWORD_UNSPECIFIED",
            "enum": [
                "INVESTMENT_STEWARDSHIP_FIXED_KEYWORD_UNSPECIFIED",
                "INVESTMENT_STEWARDSHIP_FIXED_KEYWORD_ACTIVIST",
                "INVESTMENT_STEWARDSHIP_FIXED_KEYWORD_BOARD_MEMBER",
                "INVESTMENT_STEWARDSHIP_FIXED_KEYWORD_BOARD_SECRETARY",
                "INVESTMENT_STEWARDSHIP_FIXED_KEYWORD_BOARD_DIVERSITY",
                "INVESTMENT_STEWARDSHIP_FIXED_KEYWORD_CEO",
                "INVESTMENT_STEWARDSHIP_FIXED_KEYWORD_CHAIRMAN",
                "INVESTMENT_STEWARDSHIP_FIXED_KEYWORD_CYBER_SECURITY",
                "INVESTMENT_STEWARDSHIP_FIXED_KEYWORD_INVESTOR_RELATIONS",
                "INVESTMENT_STEWARDSHIP_FIXED_KEYWORD_M_AND_A",
                "INVESTMENT_STEWARDSHIP_FIXED_KEYWORD_OPIOIDS",
                "INVESTMENT_STEWARDSHIP_FIXED_KEYWORD_POLITICAL_ACTIVITIES",
                "INVESTMENT_STEWARDSHIP_FIXED_KEYWORD_PROXY_ACCESS",
                "INVESTMENT_STEWARDSHIP_FIXED_KEYWORD_PROXY_CONTEST",
                "INVESTMENT_STEWARDSHIP_FIXED_KEYWORD_PURPOSE",
                "INVESTMENT_STEWARDSHIP_FIXED_KEYWORD_SPLIT_VOTE",
                "INVESTMENT_STEWARDSHIP_FIXED_KEYWORD_SUCCESSION_PLANNING",
                "INVESTMENT_STEWARDSHIP_FIXED_KEYWORD_TCFD",
                "INVESTMENT_STEWARDSHIP_FIXED_KEYWORD_UNGC"
            ]
        },
        "v1InvestmentStewardshipFormat": {
            "description": "- INVESTMENT_STEWARDSHIP_FORMAT_UNSPECIFIED: Unspecified\n - INVESTMENT_STEWARDSHIP_FORMAT_IN_PERSON: In person\n - INVESTMENT_STEWARDSHIP_FORMAT_CONF_CALL: Conference Call\n - INVESTMENT_STEWARDSHIP_FORMAT_EMAIL: Email\n - INVESTMENT_STEWARDSHIP_FORMAT_INTERNAL_TRACKING: Internal tracking",
            "type": "string",
            "title": "Investment Stewardship format field",
            "default": "INVESTMENT_STEWARDSHIP_FORMAT_UNSPECIFIED",
            "enum": [
                "INVESTMENT_STEWARDSHIP_FORMAT_UNSPECIFIED",
                "INVESTMENT_STEWARDSHIP_FORMAT_IN_PERSON",
                "INVESTMENT_STEWARDSHIP_FORMAT_CONF_CALL",
                "INVESTMENT_STEWARDSHIP_FORMAT_EMAIL",
                "INVESTMENT_STEWARDSHIP_FORMAT_INTERNAL_TRACKING"
            ]
        },
        "v1InvestmentStewardshipInitiator": {
            "description": "- INVESTMENT_STEWARDSHIP_INITIATOR_UNSPECIFIED: Unspecified\n - INVESTMENT_STEWARDSHIP_INITIATOR_BIS: BIS\n - INVESTMENT_STEWARDSHIP_INITIATOR_COMPANY: Company\n - INVESTMENT_STEWARDSHIP_INITIATOR_ACTIVIST: Activist\n - INVESTMENT_STEWARDSHIP_INITIATOR_ADVISOR_CONSULTANT: Advisor/Consultant\n - INVESTMENT_STEWARDSHIP_INITIATOR_OTHER: Other",
            "type": "string",
            "title": "Investment Stewardship initiated by field",
            "default": "INVESTMENT_STEWARDSHIP_INITIATOR_UNSPECIFIED",
            "enum": [
                "INVESTMENT_STEWARDSHIP_INITIATOR_UNSPECIFIED",
                "INVESTMENT_STEWARDSHIP_INITIATOR_BIS",
                "INVESTMENT_STEWARDSHIP_INITIATOR_COMPANY",
                "INVESTMENT_STEWARDSHIP_INITIATOR_ACTIVIST",
                "INVESTMENT_STEWARDSHIP_INITIATOR_ADVISOR_CONSULTANT",
                "INVESTMENT_STEWARDSHIP_INITIATOR_OTHER"
            ]
        },
        "v1InvestmentStewardshipOutcome": {
            "description": "- INVESTMENT_STEWARDSHIP_OUTCOME_UNSPECIFIED: Unspecified or N/A\n - INVESTMENT_STEWARDSHIP_OUTCOME_LIKELY_CHANGE: Likely to make change\n - INVESTMENT_STEWARDSHIP_OUTCOME_UNLIKELY_CHANGE: Unlikely to make change\n - INVESTMENT_STEWARDSHIP_OUTCOME_ALREADY_CHANGED: Already made change\n - INVESTMENT_STEWARDSHIP_OUTCOME_POLICY_SOCIALIZATION: Policy Socialization",
            "type": "string",
            "title": "Investment stewardship outcome enums",
            "default": "INVESTMENT_STEWARDSHIP_OUTCOME_UNSPECIFIED",
            "enum": [
                "INVESTMENT_STEWARDSHIP_OUTCOME_UNSPECIFIED",
                "INVESTMENT_STEWARDSHIP_OUTCOME_LIKELY_CHANGE",
                "INVESTMENT_STEWARDSHIP_OUTCOME_UNLIKELY_CHANGE",
                "INVESTMENT_STEWARDSHIP_OUTCOME_ALREADY_CHANGED",
                "INVESTMENT_STEWARDSHIP_OUTCOME_POLICY_SOCIALIZATION"
            ]
        },
        "v1InvestmentStewardshipScore": {
            "description": "- INVESTMENT_STEWARDSHIP_SCORE_UNSPECIFIED: N/A\n - INVESTMENT_STEWARDSHIP_SCORE_POSITIVE: positive\n - INVESTMENT_STEWARDSHIP_SCORE_NEUTRAL: neutral\n - INVESTMENT_STEWARDSHIP_SCORE_NEGATIVE: negative",
            "type": "string",
            "title": "Investment Stewardship score field",
            "default": "INVESTMENT_STEWARDSHIP_SCORE_UNSPECIFIED",
            "enum": [
                "INVESTMENT_STEWARDSHIP_SCORE_UNSPECIFIED",
                "INVESTMENT_STEWARDSHIP_SCORE_POSITIVE",
                "INVESTMENT_STEWARDSHIP_SCORE_NEUTRAL",
                "INVESTMENT_STEWARDSHIP_SCORE_NEGATIVE"
            ]
        },
        "v1InvestmentStewardshipTimeFrame": {
            "description": "- INVESTMENT_STEWARDSHIP_TIME_FRAME_UNSPECIFIED: Unspecified or N/A\n - INVESTMENT_STEWARDSHIP_TIME_FRAME_IMMEDIATE: Immediate\n - INVESTMENT_STEWARDSHIP_TIME_FRAME_SHORT_TERM: Short Term (\u003c1 yr)\n - INVESTMENT_STEWARDSHIP_TIME_FRAME_MEDIUM_TERM: Medium Term (1-2 yrs)\n - INVESTMENT_STEWARDSHIP_TIME_FRAME_LONG_TERM: Long Term (2+ yrs)",
            "type": "string",
            "title": "Investment stewardship time frame enums",
            "default": "INVESTMENT_STEWARDSHIP_TIME_FRAME_UNSPECIFIED",
            "enum": [
                "INVESTMENT_STEWARDSHIP_TIME_FRAME_UNSPECIFIED",
                "INVESTMENT_STEWARDSHIP_TIME_FRAME_IMMEDIATE",
                "INVESTMENT_STEWARDSHIP_TIME_FRAME_SHORT_TERM",
                "INVESTMENT_STEWARDSHIP_TIME_FRAME_MEDIUM_TERM",
                "INVESTMENT_STEWARDSHIP_TIME_FRAME_LONG_TERM"
            ]
        },
        "v1InvestmentStewardshipTopic": {
            "description": "- INVESTMENT_STEWARDSHIP_TOPIC_UNSPECIFIED: Unspecified or N/A\n - INVESTMENT_STEWARDSHIP_TOPIC_GOVERNANCE_STRUCTURE: Governance Structure\n - INVESTMENT_STEWARDSHIP_TOPIC_BOARD_COMPOSITION: Board Composition \u0026 Effectiveness\n - INVESTMENT_STEWARDSHIP_TOPIC_EXECUTIVE_MANAGEMENT: Executive Management\n - INVESTMENT_STEWARDSHIP_TOPIC_BUSINESS_OVERSIGHT: Business Oversight/Risk Management\n - INVESTMENT_STEWARDSHIP_TOPIC_CORPORATE_STRATEGY: Corporate Strategy\n - INVESTMENT_STEWARDSHIP_TOPIC_REMUNERATION: Remuneration\n - INVESTMENT_STEWARDSHIP_TOPIC_HUMAN_CAPITAL_MANAGEMENT: Human Capital Management\n - INVESTMENT_STEWARDSHIP_TOPIC_SOCIAL_RISKS_OPPORTUNITIES: Social Risks and Opportunities\n - INVESTMENT_STEWARDSHIP_TOPIC_CLIMATE_RISK_MANAGEMENT: Climate Risk Management\n - INVESTMENT_STEWARDSHIP_TOPIC_OPERATIONAL_SUSTAINABILITY: Operational Sustainability\n - INVESTMENT_STEWARDSHIP_TOPIC_ENVIRONMENT_IMPACT_MANAGEMENT: Environmental Impact Management",
            "type": "string",
            "title": "Invesetment stewardship topic enums",
            "default": "INVESTMENT_STEWARDSHIP_TOPIC_UNSPECIFIED",
            "enum": [
                "INVESTMENT_STEWARDSHIP_TOPIC_UNSPECIFIED",
                "INVESTMENT_STEWARDSHIP_TOPIC_GOVERNANCE_STRUCTURE",
                "INVESTMENT_STEWARDSHIP_TOPIC_BOARD_COMPOSITION",
                "INVESTMENT_STEWARDSHIP_TOPIC_EXECUTIVE_MANAGEMENT",
                "INVESTMENT_STEWARDSHIP_TOPIC_BUSINESS_OVERSIGHT",
                "INVESTMENT_STEWARDSHIP_TOPIC_CORPORATE_STRATEGY",
                "INVESTMENT_STEWARDSHIP_TOPIC_REMUNERATION",
                "INVESTMENT_STEWARDSHIP_TOPIC_HUMAN_CAPITAL_MANAGEMENT",
                "INVESTMENT_STEWARDSHIP_TOPIC_SOCIAL_RISKS_OPPORTUNITIES",
                "INVESTMENT_STEWARDSHIP_TOPIC_CLIMATE_RISK_MANAGEMENT",
                "INVESTMENT_STEWARDSHIP_TOPIC_OPERATIONAL_SUSTAINABILITY",
                "INVESTMENT_STEWARDSHIP_TOPIC_ENVIRONMENT_IMPACT_MANAGEMENT"
            ]
        },
        "v1InvestmentStewardshipTopicDetails": {
            "type": "object",
            "title": "Investment stewardship topic",
            "properties": {
                "topicName": {
                    "title": "Topic field",
                    "$ref": "#/definitions/v1InvestmentStewardshipTopic"
                },
                "outcome": {
                    "title": "Expected outcome field",
                    "$ref": "#/definitions/v1InvestmentStewardshipOutcome"
                },
                "timeframe": {
                    "title": "Change time frame field",
                    "$ref": "#/definitions/v1InvestmentStewardshipTimeFrame"
                },
                "assessment": {
                    "title": "Topic assessment field",
                    "$ref": "#/definitions/v1InvestmentStewardshipAssessment"
                }
            }
        },
        "v1NoteState": {
            "description": "- NOTE_STATE_UNSPECIFIED: The NoteStatus has not been specified\n - NOTE_STATE_REGULAR: The note is a regular note\n - NOTE_STATE_DRAFT: The note is a draft note\n - NOTE_STATE_DELETED: The note is deleted\n - NOTE_STATE_INVALID: The note is auto deleted and marked as invalid\nthat deleted from Aladdin Research team either from index program or bulk load failure",
            "type": "string",
            "title": "NoteState specifies the type of research note state (regular, draft, deleted)",
            "default": "NOTE_STATE_UNSPECIFIED",
            "enum": [
                "NOTE_STATE_UNSPECIFIED",
                "NOTE_STATE_REGULAR",
                "NOTE_STATE_DRAFT",
                "NOTE_STATE_DELETED",
                "NOTE_STATE_INVALID"
            ]
        },
        "v1PublishPreference": {
            "description": "The user's Research Note publish preferences.",
            "type": "object",
            "properties": {
                "defaultNoteCategory": {
                    "type": "string",
                    "title": "The user's saved default research note category"
                },
                "defaultPermissionGroups": {
                    "type": "array",
                    "title": "The user's saved default research note permission group",
                    "items": {
                        "type": "string"
                    }
                },
                "canPublishNote": {
                    "type": "boolean",
                    "title": "Flag to determine if user has the perms to publish new research notes"
                }
            }
        },
        "v1ResearchNote": {
            "description": "Research describes...",
            "type": "object",
            "properties": {
                "id": {
                    "description": "ID describes the computer or human assigned resource identifier.\nThe research note id.",
                    "type": "string"
                },
                "author": {
                    "description": "The author of the research note.",
                    "type": "string"
                },
                "creator": {
                    "description": "The creator of the research note.",
                    "type": "string"
                },
                "subject": {
                    "description": "The subject (title) of the research note.",
                    "type": "string"
                },
                "noteCategory": {
                    "description": "The note category.",
                    "type": "string"
                },
                "keywords": {
                    "description": "The keywords.",
                    "type": "array",
                    "items": {
                        "type": "string"
                    }
                },
                "publishTime": {
                    "description": "The publish time.",
                    "type": "string",
                    "format": "date-time"
                },
                "note": {
                    "description": "The note textual content.",
                    "type": "string"
                },
                "noteState": {
                    "description": "The research note state.",
                    "$ref": "#/definitions/v1NoteState"
                },
                "selectedPermissionGroups": {
                    "type": "array",
                    "title": "The selected permission groups.\n(-- aip.dev/beta-blocker: refactor to use permission common resource when it's ready --)",
                    "items": {
                        "type": "string"
                    }
                },
                "entities": {
                    "type": "array",
                    "title": "The entities (e.g. securities, issuers, etc.) are associated with this research note",
                    "items": {
                        "$ref": "#/definitions/typesEntityId"
                    }
                },
                "brokerId": {
                    "type": "string",
                    "title": "represents broker"
                },
                "investmentStewardshipDetail": {
                    "title": "Investment stewardship note specific fields",
                    "$ref": "#/definitions/v1InvestmentStewardshipDetail"
                },
                "researchStrategyDetail": {
                    "title": "Research strategy note specific fields",
                    "$ref": "#/definitions/v1ResearchStrategyDetail"
                },
                "expiringPermissionGroups": {
                    "type": "array",
                    "title": "The expiring permissions group field",
                    "items": {
                        "$ref": "#/definitions/v1ExpiringPermissionGroup"
                    }
                },
                "noteHtml": {
                    "type": "string",
                    "title": "The note in HTML format"
                }
            }
        },
        "v1ResearchStrategyDetail": {
            "type": "object",
            "title": "The research strategy note template",
            "properties": {
                "researchStrategy": {
                    "description": "The research strategy name.",
                    "type": "string"
                },
                "researchStrategyStatus": {
                    "description": "The research strategy status.",
                    "type": "string"
                },
                "researchStrategyAction": {
                    "description": "The research strategy action.",
                    "type": "string"
                }
            }
        },
        "v1SearchPreference": {
            "description": "The user's Research Note search preferences.",
            "type": "object",
            "properties": {
                "searchFilters": {
                    "type": "object",
                    "title": "Map to hold user's search filters",
                    "additionalProperties": {
                        "type": "string"
                    }
                },
                "searchParameters": {
                    "type": "object",
                    "title": "Map to hold user's search parameters (internal and exposure lookback periods, etc.)",
                    "additionalProperties": {
                        "type": "string"
                    }
                }
            }
        },
        "v1SearchResearchNotesResponse": {
            "type": "object",
            "title": "The response message for ResearchAPI.ListResearchs.\n(-- api-linter: core::0158::response-next-page-token-field=disabled\n aip.dev/not-precedent: We need to do this because this is irrelevant at this context --)",
            "properties": {
                "researchNotes": {
                    "description": "researchs to be returned.",
                    "type": "array",
                    "items": {
                        "$ref": "#/definitions/v1ResearchNote"
                    }
                }
            }
        },
        "v1UserPreferences": {
            "description": "The response message for ResearchAPI.GetUserPreferences.",
            "type": "object",
            "properties": {
                "publishPreference": {
                    "title": "Research Note publish preferences",
                    "$ref": "#/definitions/v1PublishPreference"
                },
                "searchPreference": {
                    "title": "Research Note search preferences",
                    "$ref": "#/definitions/v1SearchPreference"
                }
            }
        }
    },
    "securityDefinitions": {
        "APIKeyHeader": {
            "type": "apiKey",
            "name": "VND.com.blackrock.API-Key",
            "in": "header"
        },
        "basicAuth": {
            "type": "basic"
        }
    },
    "security": [
        {
            "APIKeyHeader": [],
            "basicAuth": []
        }
    ],
    "tags": [
        {
            "name": "Access.Internal"
        }
    ],
    "x-access-level": "Public"
}